AUTHORS
COPYING
ChangeLog
LINKS
MANIFEST.in
Makefile
PKG-INFO
README
TESTS
TODO
WISHLIST
ez_setup.py
mtstat.spec
setup.cfg
setup.py
debian/changelog
debian/compat
debian/control
debian/copyright
debian/dirs
debian/docs
debian/examples
debian/manpages
debian/rules
debian/watch
docs/Makefile
docs/counter-rollovers.html
docs/counter-rollovers.txt
docs/dstat.1
docs/dstat.1.html
docs/dstat.1.txt
docs/examples.html
docs/examples.txt
docs/performance.html
docs/performance.txt
docs/plugins.html
docs/plugins.txt
docs/screen.html
docs/screen.txt
examples/curstest
examples/mmpipe.py
examples/mstat.py
examples/read.py
examples/tdbtest
mtstat/__init__.py
mtstat/mtstat.py
mtstat.egg-info/PKG-INFO
mtstat.egg-info/SOURCES.txt
mtstat.egg-info/dependency_links.txt
mtstat.egg-info/entry_points.txt
mtstat.egg-info/top_level.txt
mtstat/plugins/__init__.py
mtstat/plugins/mtstat_app.py
mtstat/plugins/mtstat_battery.py
mtstat/plugins/mtstat_clock.py
mtstat/plugins/mtstat_dbus.py
mtstat/plugins/mtstat_freespace.py
mtstat/plugins/mtstat_gpfs.py
mtstat/plugins/mtstat_gpfsop.py
mtstat/plugins/mtstat_nfs3.py
mtstat/plugins/mtstat_nfs3op.py
mtstat/plugins/mtstat_nfsd3.py
mtstat/plugins/mtstat_nfsd3op.py
mtstat/plugins/mtstat_postfix.py
mtstat/plugins/mtstat_rpc.py
mtstat/plugins/mtstat_rpcd.py
mtstat/plugins/mtstat_sendmail.py
mtstat/plugins/mtstat_thermal.py
mtstat/plugins/mtstat_utmp.py
mtstat/plugins/mtstat_wifi.py
proc/diskstats-2.6.11
proc/partitions-2.4.21
proc/partitions-2.4.24
proc/partitions-2.6.11
proc/stat-2.4.21
proc/stat-2.4.24
proc/stat-2.6.11
