Metadata-Version: 1.0
Name: mtstat
Version: 0.7.3
Summary: A versatile resource statistics tool
Home-page: http://trac.inaugust.com/mtstat/
Author: Monty Taylor
Author-email: monty@inaugust.com
License: UNKNOWN
Platform: UNKNOWN
